lobsang/__init__.py
lobsang/chat.py
lobsang/messages.py
lobsang/answers/__init__.py
lobsang/answers/base.py
lobsang/answers/json.py
lobsang/answers/text.py
lobsang/llms/__init__.py
lobsang/llms/base.py
lobsang/llms/fake.py
lobsang/llms/openai.py
lobsang-0.1.0.dist-info/METADATA
lobsang-0.1.0.dist-info/WHEEL
lobsang-0.1.0.dist-info/licenses/LICENSE
lobsang-0.1.0.dist-info/RECORD
