Metadata-Version: 2.1
Name: lobsang
Version: 0.1.0
Summary: A simple framework to interact with conversational LLMs
Project-URL: Homepage, https://github.com/cereisen/lobsang
License-File: LICENSE
Keywords: chat,framework,llm
Classifier: License :: OSI Approved :: MIT License
Classifier: Operating System :: OS Independent
Classifier: Programming Language :: Python :: 3
Requires-Python: >=3.11
Requires-Dist: jsonschema<5,>=4.18.6
Requires-Dist: openai<1,>=0.27.8
Provides-Extra: dev
Requires-Dist: black==23.3.0; extra == 'dev'
Requires-Dist: pylint==2.8.2; extra == 'dev'
